epnel/__init__.py
epnel/interpreter.py
epnel/parser.py
epnel/repl.py
epnel-0.0.3.dist-info/LICENSE
epnel-0.0.3.dist-info/METADATA
epnel-0.0.3.dist-info/WHEEL
epnel-0.0.3.dist-info/entry_points.txt
epnel-0.0.3.dist-info/top_level.txt
epnel-0.0.3.dist-info/RECORD
