Metadata-Version: 2.1
Name: epnel
Version: 0.0.3
Summary: Esoteric Polish Notation Evaluation Language
Home-page: https://gitlab.com/wykwit/epnel
Author: wykwit
Author-email: wykwit@disroot.org
License: GPLv3
License-File: LICENSE
